[ 
    [{"piece": "Rook", "color": "b"}  , {"piece": "Pawn", "color": "b"}, null, null, null, null, {"piece": "Pawn", "color": "w"}, {"piece": "Rook"   , "color": "w"}],
    [{"piece": "Knight", "color": "b"}, {"piece": "Pawn", "color": "b"}, null, null, null, null, {"piece": "Pawn", "color": "w"}, {"piece": "Knight" , "color": "w"}],
    [{"piece": "Bishop", "color": "b"}, {"piece": "Pawn", "color": "b"}, null, null, null, null, {"piece": "Pawn", "color": "w"}, {"piece": "Bishop" , "color": "w"}],
    [{"piece": "Queen", "color": "b"} , {"piece": "Pawn", "color": "b"}, null, null, null, null, {"piece": "Pawn", "color": "w"}, {"piece": "Queen"  , "color": "w"}],
    [{"piece": "King", "color": "b"}  , {"piece": "Pawn", "color": "b"}, null, null, null, null, {"piece": "Pawn", "color": "w"}, {"piece": "King"   , "color": "w"}],
    [{"piece": "Bishop", "color": "b"}, {"piece": "Pawn", "color": "b"}, null, null, null, null, {"piece": "Pawn", "color": "w"}, {"piece": "Bishop" , "color": "w"}],
    [{"piece": "Knight", "color": "b"}, {"piece": "Pawn", "color": "b"}, null, null, null, null, {"piece": "Pawn", "color": "w"}, {"piece": "Knight" , "color": "w"}],
    [{"piece": "Rook", "color": "b"}  , {"piece": "Pawn", "color": "b"}, null, null, null, null, {"piece": "Pawn", "color": "w"}, {"piece": "Rook"   , "color": "w"}]
]